{
    "name": "MSatuan",
    "fields": [
        {
            "fieldName": "nama",
            "fieldType": "String",
            "fieldValidateRules": [
                "required"
            ]
        },
        {
            "fieldName": "deskripsi",
            "fieldType": "String"
        },
        {
            "fieldName": "status",
            "fieldType": "Status",
            "fieldValues": "ACT,DIS,DEL"
        },
        {
            "fieldName": "createdOn",
            "fieldType": "LocalDate"
        }
    ],
    "relationships": [
        {
            "relationshipType": "one-to-many",
            "relationshipName": "material",
            "otherEntityName": "mMaterial",
            "otherEntityRelationshipName": "satuan"
        }
    ],
    "changelogDate": "20190117080951",
    "entityTableName": "m_satuan",
    "dto": "no",
    "pagination": "pagination",
    "service": "serviceImpl",
    "jpaMetamodelFiltering": false,
    "fluentMethods": true,
    "clientRootFolder": "",
    "applications": "*"
}